pinax/__init__.py
pinax/comments/__init__.py
pinax/comments/admin.py
pinax/comments/apps.py
pinax/comments/conf.py
pinax/comments/forms.py
pinax/comments/hooks.py
pinax/comments/models.py
pinax/comments/signals.py
pinax/comments/urls.py
pinax/comments/views.py
pinax/comments/migrations/0001_initial.py
pinax/comments/migrations/__init__.py
pinax/comments/templatetags/__init__.py
pinax/comments/templatetags/pinax_comments_tags.py
pinax/comments/tests/__init__.py
pinax/comments/tests/models.py
pinax/comments/tests/test.py
pinax/comments/tests/tests.py
pinax/comments/tests/urls.py
pinax_comments-2.0.0.dist-info/AUTHORS
pinax_comments-2.0.0.dist-info/LICENSE
pinax_comments-2.0.0.dist-info/METADATA
pinax_comments-2.0.0.dist-info/WHEEL
pinax_comments-2.0.0.dist-info/top_level.txt
pinax_comments-2.0.0.dist-info/RECORD
